benchmark_comparison.py
flock_ai_api.py
flock_mcp_server.py
flock_webui.py
flockparsecli.py
gpu_controller.py
gpu_router_daemon.py
logging_config.py
sollol_compat.py
docs/architecture.md
flockparser-1.0.9.dist-info/licenses/LICENSE
showcase/process_arxiv_papers.py
tools/verify_sollol_access.py
venv/bin/dumppdf.py
venv/bin/pdf2txt.py
flockparser-1.0.9.dist-info/METADATA
flockparser-1.0.9.dist-info/WHEEL
flockparser-1.0.9.dist-info/entry_points.txt
flockparser-1.0.9.dist-info/top_level.txt
flockparser-1.0.9.dist-info/RECORD
