Metadata-Version: 2.4
Name: flockparser
Version: 1.0.9
Summary: Distributed document RAG system with intelligent GPU/CPU orchestration
Home-page: https://github.com/BenevolentJoker-JohnL/FlockParser
Author: BenevolentJoker (John L.)
Author-email: "BenevolentJoker (John L.)" <benevolentjoker@gmail.com>
License: MIT
Project-URL: Homepage, https://github.com/BenevolentJoker-JohnL/FlockParser
Project-URL: Documentation, https://github.com/BenevolentJoker-JohnL/FlockParser#readme
Project-URL: Repository, https://github.com/BenevolentJoker-JohnL/FlockParser
Project-URL: Bug Tracker, https://github.com/BenevolentJoker-JohnL/FlockParser/issues
Project-URL: Demo Video, https://youtu.be/M-HjXkWYRLM
Keywords: rag,retrieval-augmented-generation,distributed-systems,document-processing,gpu-acceleration,ollama,chromadb,pdf-processing,ocr,ai,machine-learning,nlp
Classifier: Development Status :: 4 - Beta
Classifier: Intended Audience :: Developers
Classifier: Intended Audience :: Science/Research
Classifier: License :: OSI Approved :: MIT License
Classifier: Operating System :: OS Independent
Classifier: Programming Language :: Python :: 3
Classifier: Programming Language :: Python :: 3.10
Classifier: Programming Language :: Python :: 3.11
Classifier: Programming Language :: Python :: 3.12
Classifier: Topic :: Scientific/Engineering :: Artificial Intelligence
Classifier: Topic :: Text Processing :: General
Classifier: Topic :: System :: Distributed Computing
Requires-Python: >=3.10
License-File: LICENSE
Requires-Dist: fastapi>=0.103.1
Requires-Dist: uvicorn>=0.23.2
Requires-Dist: python-multipart>=0.0.6
Requires-Dist: pdfplumber>=0.10.2
Requires-Dist: PyPDF2>=3.0.0
Requires-Dist: pypdf>=3.15.1
Requires-Dist: pytesseract>=0.3.10
Requires-Dist: Pillow>=10.0.0
Requires-Dist: pdf2image>=1.16.0
Requires-Dist: python-docx>=0.8.11
Requires-Dist: markdown>=3.4.4
Requires-Dist: chromadb>=0.4.13
Requires-Dist: ollama>=0.1.4
Requires-Dist: numpy>=1.24.0
Requires-Dist: requests>=2.31.0
Requires-Dist: mcp>=1.0.0
Requires-Dist: streamlit>=1.40.0
Requires-Dist: pytest>=7.4.0
Requires-Dist: pytest-timeout>=2.1.0
Requires-Dist: sollol-flockparser>=0.9.60
Provides-Extra: dev
Requires-Dist: pytest>=7.4.0; extra == "dev"
Requires-Dist: pytest-timeout>=2.1.0; extra == "dev"
Requires-Dist: black>=23.0.0; extra == "dev"
Requires-Dist: flake8>=6.0.0; extra == "dev"
Provides-Extra: ocr
Requires-Dist: ocrmypdf>=15.4.0; extra == "ocr"
Dynamic: author
Dynamic: home-page
Dynamic: license-file
Dynamic: requires-python
